{
  "date": "2026-07-02",
  "updated_at": "2026-07-02 08:37",
  "headline_summary": "米伊の対話が始まるもホルムズ海峡の状況は不安定なまま。米伊の対話は、ホルムズ海峡の状況を改善するための重要なステップとなるかもしれないが、現在の状況は依然として不安定である。",
  "top_topics": [
    {
      "title": "ホルムズ海峡の状況",
      "summary": "ホルムズ海峡は再び閉鎖され、米伊の対話は始まったが、状況は依然として不安定である。"
    },
    {
      "title": "米伊の対話",
      "summary": "米伊の対話は始まったが、米伊の対立は依然として深刻である。"
    },
    {
      "title": "中東の停戦",
      "summary": "中東の停戦は実現していない。戦争は依然として続いている。"
    }
  ],
  "impact_on_japan": [
    "日本のエネルギー需給に影響を与える可能性がある。"
  ],
  "ai_forecast": [
    "ホルムズ海峡の状況が改善されない場合、世界のエネルギー需給が不安定になる可能性がある。",
    "米伊の対立が深刻化する可能性がある。",
    "中東の停戦が実現しない場合、世界の安全保障が不安定になる可能性がある。"
  ],
  "diff": {
    "new_topics": [
      "ホルムズ海峡の状況",
      "中東の停戦",
      "米伊の対話"
    ],
    "removed_topics": [
      "ホルムズ海峡の安全保障が懸念される",
      "ホルムズ海峡の石油輸送量が増加",
      "米伊の対話が続く"
    ]
  }
}